uclacatalog/__init__.py
uclacatalog/api.py
uclacatalog/requesthandler.py
uclacatalog/model/__init__.py
uclacatalog/model/course.py
uclacatalog/model/section.py
uclacatalog/parser/__init__.py
uclacatalog/parser/catalogparser.py
uclacatalog/parser/sectionparser.py
uclacatalog-1.1.0.dist-info/LICENSE
uclacatalog-1.1.0.dist-info/METADATA
uclacatalog-1.1.0.dist-info/WHEEL
uclacatalog-1.1.0.dist-info/top_level.txt
uclacatalog-1.1.0.dist-info/RECORD
