Metadata-Version: 2.1
Name: uclacatalog
Version: 1.1.0
Summary: A Python library to retrieve course and section information from the UCLA Registrar
Home-page: https://github.com/nnhien/uclacatalog
Author: Nicholas Nhien
Author-email: nknhien@ucla.edu
License: UNKNOWN
Platform: UNKNOWN
Classifier: Programming Language :: Python :: 3
Classifier: Development Status :: 3 - Alpha
Classifier: License :: OSI Approved :: GNU Affero General Public License v3 or later (AGPLv3+)
Classifier: Operating System :: OS Independent
Classifier: Topic :: Internet :: WWW/HTTP :: Indexing/Search
Requires-Python: >=3.6
Requires-Dist: beautifulsoup4
Requires-Dist: lxml
Requires-Dist: requests
